databricks_client/__init__.py
databricks_client-0.0.3.dist-info/METADATA
databricks_client-0.0.3.dist-info/WHEEL
databricks_client-0.0.3.dist-info/top_level.txt
databricks_client-0.0.3.dist-info/RECORD
