Metadata-Version: 2.1
Name: databricks-client
Version: 0.0.3
Summary: REST client for Databricks
Home-page: https://github.com/microsoft/DataOps
Author: Alexandre Gattiker
Author-email: algattik@microsoft.com
License: UNKNOWN
Platform: UNKNOWN
Classifier: Programming Language :: Python :: 3
Classifier: License :: OSI Approved :: MIT License
Classifier: Operating System :: OS Independent
Requires-Dist: requests
Provides-Extra: azurecli
Requires-Dist: azure-core ; extra == 'azurecli'
